dicomanonymizer/__init__.py
dicomanonymizer/anonymizer.py
dicomanonymizer/dicomfields.py
dicomanonymizer/simpledicomanonymizer.py
DicomAnonymizer-0.0.1.dist-info/METADATA
DicomAnonymizer-0.0.1.dist-info/WHEEL
DicomAnonymizer-0.0.1.dist-info/entry_points.txt
DicomAnonymizer-0.0.1.dist-info/top_level.txt
DicomAnonymizer-0.0.1.dist-info/RECORD
